{
  "info": {
    "name": "Stock Management API",
    "description": "Complete API collection for Stock Management System",
    "schema": "https://schema.getpostman.com/json/collection/v2.1.0/collection.json",
    "version": "1.0.0"
  },
  "auth": {
    "type": "bearer",
    "bearer": [
      {
        "key": "token",
        "value": "{{authToken}}",
        "type": "string"
      }
    ]
  },
  "variable": [
    {
      "key": "baseUrl",
      "value": "https://stock-management-backend-lz5t.onrender.com/api",
      "type": "string"
    },
    {
      "key": "authToken",
      "value": "",
      "type": "string"
    }
  ],
  "item": [
    {
      "name": "System",
      "item": [
        {
          "name": "Health Check",
          "request": {
            "method": "GET",
            "header": [],
            "url": {
              "raw": "{{baseUrl}}/health",
              "host": ["{{baseUrl}}"],
              "path": ["health"]
            }
          }
        },
        {
          "name": "Test Database Connection",
          "request": {
            "method": "GET",
            "header": [],
            "url": {
              "raw": "{{baseUrl}}/test-connection",
              "host": ["{{baseUrl}}"],
              "path": ["test-connection"]
            }
          }
        },
        {
          "name": "Debug Routes",
          "request": {
            "method": "GET",
            "header": [],
            "url": {
              "raw": "{{baseUrl}}/debug-routes",
              "host": ["{{baseUrl}}"],
              "path": ["debug-routes"]
            }
          }
        }
      ]
    },
    {
      "name": "Authentication",
      "item": [
        {
          "name": "Register User",
          "event": [
            {
              "listen": "test",
              "script": {
                "exec": [
                  "if (pm.response.code === 201) {",
                  "    const response = pm.response.json();",
                  "    if (response.token) {",
                  "        pm.environment.set('authToken', response.token);",
                  "        pm.globals.set('authToken', response.token);",
                  "    }",
                  "    pm.test('User registered successfully', function () {",
                  "        pm.expect(response.success).to.be.true;",
                  "        pm.expect(response.token).to.exist;",
                  "    });",
                  "}"
                ]
              }
            }
          ],
          "request": {
            "method": "POST",
            "header": [
              {
                "key": "Content-Type",
                "value": "application/json"
              }
            ],
            "body": {
              "mode": "raw",
              "raw": "{\n    \"name\": \"Test User\",\n    \"phone\": \"0781234567\",\n    \"email\": \"test@example.com\",\n    \"password\": \"password123\"\n}"
            },
            "url": {
              "raw": "{{baseUrl}}/auth/register",
              "host": ["{{baseUrl}}"],
              "path": ["auth", "register"]
            }
          }
        },
        {
          "name": "Login User",
          "event": [
            {
              "listen": "test",
              "script": {
                "exec": [
                  "if (pm.response.code === 200) {",
                  "    const response = pm.response.json();",
                  "    if (response.token) {",
                  "        pm.environment.set('authToken', response.token);",
                  "        pm.globals.set('authToken', response.token);",
                  "    }",
                  "    pm.test('Login successful', function () {",
                  "        pm.expect(response.success).to.be.true;",
                  "        pm.expect(response.token).to.exist;",
                  "    });",
                  "}"
                ]
              }
            }
          ],
          "request": {
            "method": "POST",
            "header": [
              {
                "key": "Content-Type",
                "value": "application/json"
              }
            ],
            "body": {
              "mode": "raw",
              "raw": "{\n    \"email\": \"test@example.com\",\n    \"password\": \"password123\"\n}"
            },
            "url": {
              "raw": "{{baseUrl}}/auth/login",
              "host": ["{{baseUrl}}"],
              "path": ["auth", "login"]
            }
          }
        }
      ]
    },
    {
      "name": "Products",
      "item": [
        {
          "name": "Create Product",
          "request": {
            "auth": {
              "type": "bearer",
              "bearer": [
                {
                  "key": "token",
                  "value": "{{authToken}}",
                  "type": "string"
                }
              ]
            },
            "method": "POST",
            "header": [
              {
                "key": "Content-Type",
                "value": "application/json"
              }
            ],
            "body": {
              "mode": "raw",
              "raw": "{\n    \"name\": \"Ibirayi\"\n}"
            },
            "url": {
              "raw": "{{baseUrl}}/products",
              "host": ["{{baseUrl}}"],
              "path": ["products"]
            }
          }
        },
        {
          "name": "Get All Products",
          "request": {
            "auth": {
              "type": "bearer",
              "bearer": [
                {
                  "key": "token",
                  "value": "{{authToken}}",
                  "type": "string"
                }
              ]
            },
            "method": "GET",
            "header": [],
            "url": {
              "raw": "{{baseUrl}}/products",
              "host": ["{{baseUrl}}"],
              "path": ["products"]
            }
          }
        },
        {
          "name": "Get Single Product",
          "request": {
            "auth": {
              "type": "bearer",
              "bearer": [
                {
                  "key": "token",
                  "value": "{{authToken}}",
                  "type": "string"
                }
              ]
            },
            "method": "GET",
            "header": [],
            "url": {
              "raw": "{{baseUrl}}/products/1",
              "host": ["{{baseUrl}}"],
              "path": ["products", "1"]
            }
          }
        },
        {
          "name": "Update Product",
          "request": {
            "auth": {
              "type": "bearer",
              "bearer": [
                {
                  "key": "token",
                  "value": "{{authToken}}",
                  "type": "string"
                }
              ]
            },
            "method": "PUT",
            "header": [
              {
                "key": "Content-Type",
                "value": "application/json"
              }
            ],
            "body": {
              "mode": "raw",
              "raw": "{\n    \"name\": \"Ibirayi Updated\"\n}"
            },
            "url": {
              "raw": "{{baseUrl}}/products/1",
              "host": ["{{baseUrl}}"],
              "path": ["products", "1"]
            }
          }
        },
        {
          "name": "Delete Product",
          "request": {
            "auth": {
              "type": "bearer",
              "bearer": [
                {
                  "key": "token",
                  "value": "{{authToken}}",
                  "type": "string"
                }
              ]
            },
            "method": "DELETE",
            "header": [],
            "url": {
              "raw": "{{baseUrl}}/products/1",
              "host": ["{{baseUrl}}"],
              "path": ["products", "1"]
            }
          }
        }
      ]
    },
    {
      "name": "Stock Management",
      "item": [
        {
          "name": "Add Stock",
          "request": {
            "auth": {
              "type": "bearer",
              "bearer": [
                {
                  "key": "token",
                  "value": "{{authToken}}",
                  "type": "string"
                }
              ]
            },
            "method": "POST",
            "header": [
              {
                "key": "Content-Type",
                "value": "application/json"
              }
            ],
            "body": {
              "mode": "raw",
              "raw": "{\n    \"product_id\": 1,\n    \"quantity\": 100,\n    \"cost_price\": 800.00,\n    \"selling_price\": 1200.00\n}"
            },
            "url": {
              "raw": "{{baseUrl}}/stock",
              "host": ["{{baseUrl}}"],
              "path": ["stock"]
            }
          }
        },
        {
          "name": "Get All Stock",
          "request": {
            "auth": {
              "type": "bearer",
              "bearer": [
                {
                  "key": "token",
                  "value": "{{authToken}}",
                  "type": "string"
                }
              ]
            },
            "method": "GET",
            "header": [],
            "url": {
              "raw": "{{baseUrl}}/stock",
              "host": ["{{baseUrl}}"],
              "path": ["stock"]
            }
          }
        },
        {
          "name": "Get Single Stock",
          "request": {
            "auth": {
              "type": "bearer",
              "bearer": [
                {
                  "key": "token",
                  "value": "{{authToken}}",
                  "type": "string"
                }
              ]
            },
            "method": "GET",
            "header": [],
            "url": {
              "raw": "{{baseUrl}}/stock/1",
              "host": ["{{baseUrl}}"],
              "path": ["stock", "1"]
            }
          }
        },
        {
          "name": "Update Stock",
          "request": {
            "auth": {
              "type": "bearer",
              "bearer": [
                {
                  "key": "token",
                  "value": "{{authToken}}",
                  "type": "string"
                }
              ]
            },
            "method": "PUT",
            "header": [
              {
                "key": "Content-Type",
                "value": "application/json"
              }
            ],
            "body": {
              "mode": "raw",
              "raw": "{\n    \"product_id\": 1,\n    \"quantity\": 150,\n    \"cost_price\": 750.00,\n    \"selling_price\": 1150.00\n}"
            },
            "url": {
              "raw": "{{baseUrl}}/stock/1",
              "host": ["{{baseUrl}}"],
              "path": ["stock", "1"]
            }
          }
        },
        {
          "name": "Delete Stock",
          "request": {
            "auth": {
              "type": "bearer",
              "bearer": [
                {
                  "key": "token",
                  "value": "{{authToken}}",
                  "type": "string"
                }
              ]
            },
            "method": "DELETE",
            "header": [],
            "url": {
              "raw": "{{baseUrl}}/stock/1",
              "host": ["{{baseUrl}}"],
              "path": ["stock", "1"]
            }
          }
        }
      ]
    },
    {
      "name": "Stock Out (Sales)",
      "item": [
        {
          "name": "Add Sale",
          "request": {
            "auth": {
              "type": "bearer",
              "bearer": [
                {
                  "key": "token",
                  "value": "{{authToken}}",
                  "type": "string"
                }
              ]
            },
            "method": "POST",
            "header": [
              {
                "key": "Content-Type",
                "value": "application/json"
              }
            ],
            "body": {
              "mode": "raw",
              "raw": "{\n    \"product_id\": 1,\n    \"quantity\": 10,\n    \"selling_price\": 1200.00\n}"
            },
            "url": {
              "raw": "{{baseUrl}}/stock-out",
              "host": ["{{baseUrl}}"],
              "path": ["stock-out"]
            }
          }
        },
        {
          "name": "Get All Sales",
          "request": {
            "auth": {
              "type": "bearer",
              "bearer": [
                {
                  "key": "token",
                  "value": "{{authToken}}",
                  "type": "string"
                }
              ]
            },
            "method": "GET",
            "header": [],
            "url": {
              "raw": "{{baseUrl}}/stock-out",
              "host": ["{{baseUrl}}"],
              "path": ["stock-out"]
            }
          }
        },
        {
          "name": "Get Single Sale",
          "request": {
            "auth": {
              "type": "bearer",
              "bearer": [
                {
                  "key": "token",
                  "value": "{{authToken}}",
                  "type": "string"
                }
              ]
            },
            "method": "GET",
            "header": [],
            "url": {
              "raw": "{{baseUrl}}/stock-out/1",
              "host": ["{{baseUrl}}"],
              "path": ["stock-out", "1"]
            }
          }
        },
        {
          "name": "Update Sale",
          "request": {
            "auth": {
              "type": "bearer",
              "bearer": [
                {
                  "key": "token",
                  "value": "{{authToken}}",
                  "type": "string"
                }
              ]
            },
            "method": "PUT",
            "header": [
              {
                "key": "Content-Type",
                "value": "application/json"
              }
            ],
            "body": {
              "mode": "raw",
              "raw": "{\n    \"product_id\": 1,\n    \"quantity\": 15,\n    \"selling_price\": 1250.00\n}"
            },
            "url": {
              "raw": "{{baseUrl}}/stock-out/1",
              "host": ["{{baseUrl}}"],
              "path": ["stock-out", "1"]
            }
          }
        },
        {
          "name": "Delete Sale",
          "request": {
            "auth": {
              "type": "bearer",
              "bearer": [
                {
                  "key": "token",
                  "value": "{{authToken}}",
                  "type": "string"
                }
              ]
            },
            "method": "DELETE",
            "header": [],
            "url": {
              "raw": "{{baseUrl}}/stock-out/1",
              "host": ["{{baseUrl}}"],
              "path": ["stock-out", "1"]
            }
          }
        },
        {
          "name": "Get Stock Summary",
          "request": {
            "auth": {
              "type": "bearer",
              "bearer": [
                {
                  "key": "token",
                  "value": "{{authToken}}",
                  "type": "string"
                }
              ]
            },
            "method": "GET",
            "header": [],
            "url": {
              "raw": "{{baseUrl}}/stock-out/summary/1",
              "host": ["{{baseUrl}}"],
              "path": ["stock-out", "summary", "1"]
            }
          }
        }
      ]
    },
    {
      "name": "Expenses",
      "item": [
        {
          "name": "Add General Expense",
          "request": {
            "auth": {
              "type": "bearer",
              "bearer": [
                {
                  "key": "token",
                  "value": "{{authToken}}",
                  "type": "string"
                }
              ]
            },
            "method": "POST",
            "header": [
              {
                "key": "Content-Type",
                "value": "application/json"
              }
            ],
            "body": {
              "mode": "raw",
              "raw": "{\n    \"expense_type\": \"general\",\n    \"category\": \"Utilities\",\n    \"description\": \"Monthly electricity bill\",\n    \"amount\": 45000.00,\n    \"expense_date\": \"2024-06-18\"\n}"
            },
            "url": {
              "raw": "{{baseUrl}}/expenses",
              "host": ["{{baseUrl}}"],
              "path": ["expenses"]
            }
          }
        },
        {
          "name": "Add Specific Expense",
          "request": {
            "auth": {
              "type": "bearer",
              "bearer": [
                {
                  "key": "token",
                  "value": "{{authToken}}",
                  "type": "string"
                }
              ]
            },
            "method": "POST",
            "header": [
              {
                "key": "Content-Type",
                "value": "application/json"
              }
            ],
            "body": {
              "mode": "raw",
              "raw": "{\n    \"expense_type\": \"specific\",\n    \"product_id\": 1,\n    \"category\": \"Transportation\",\n    \"description\": \"Delivery cost for products\",\n    \"amount\": 15000.00,\n    \"expense_date\": \"2024-06-18\"\n}"
            },
            "url": {
              "raw": "{{baseUrl}}/expenses",
              "host": ["{{baseUrl}}"],
              "path": ["expenses"]
            }
          }
        },
        {
          "name": "Get All Expenses",
          "request": {
            "auth": {
              "type": "bearer",
              "bearer": [
                {
                  "key": "token",
                  "value": "{{authToken}}",
                  "type": "string"
                }
              ]
            },
            "method": "GET",
            "header": [],
            "url": {
              "raw": "{{baseUrl}}/expenses",
              "host": ["{{baseUrl}}"],
              "path": ["expenses"]
            }
          }
        },
        {
          "name": "Get Expenses by Type",
          "request": {
            "auth": {
              "type": "bearer",
              "bearer": [
                {
                  "key": "token",
                  "value": "{{authToken}}",
                  "type": "string"
                }
              ]
            },
            "method": "GET",
            "header": [],
            "url": {
              "raw": "{{baseUrl}}/expenses?expense_type=general",
              "host": ["{{baseUrl}}"],
              "path": ["expenses"],
              "query": [
                {
                  "key": "expense_type",
                  "value": "general"
                }
              ]
            }
          }
        },
        {
          "name": "Get Expenses by Category",
          "request": {
            "auth": {
              "type": "bearer",
              "bearer": [
                {
                  "key": "token",
                  "value": "{{authToken}}",
                  "type": "string"
                }
              ]
            },
            "method": "GET",
            "header": [],
            "url": {
              "raw": "{{baseUrl}}/expenses?category=Utilities",
              "host": ["{{baseUrl}}"],
              "path": ["expenses"],
              "query": [
                {
                  "key": "category",
                  "value": "Utilities"
                }
              ]
            }
          }
        },
        {
          "name": "Get Single Expense",
          "request": {
            "auth": {
              "type": "bearer",
              "bearer": [
                {
                  "key": "token",
                  "value": "{{authToken}}",
                  "type": "string"
                }
              ]
            },
            "method": "GET",
            "header": [],
            "url": {
              "raw": "{{baseUrl}}/expenses/1",
              "host": ["{{baseUrl}}"],
              "path": ["expenses", "1"]
            }
          }
        },
        {
          "name": "Update Expense",
          "request": {
            "auth": {
              "type": "bearer",
              "bearer": [
                {
                  "key": "token",
                  "value": "{{authToken}}",
                  "type": "string"
                }
              ]
            },
            "method": "PUT",
            "header": [
              {
                "key": "Content-Type",
                "value": "application/json"
              }
            ],
            "body": {
              "mode": "raw",
              "raw": "{\n    \"expense_type\": \"general\",\n    \"category\": \"Utilities\",\n    \"description\": \"Updated electricity bill\",\n    \"amount\": 50000.00,\n    \"expense_date\": \"2024-06-18\"\n}"
            },
            "url": {
              "raw": "{{baseUrl}}/expenses/1",
              "host": ["{{baseUrl}}"],
              "path": ["expenses", "1"]
            }
          }
        },
        {
          "name": "Delete Expense",
          "request": {
            "auth": {
              "type": "bearer",
              "bearer": [
                {
                  "key": "token",
                  "value": "{{authToken}}",
                  "type": "string"
                }
              ]
            },
            "method": "DELETE",
            "header": [],
            "url": {
              "raw": "{{baseUrl}}/expenses/1",
              "host": ["{{baseUrl}}"],
              "path": ["expenses", "1"]
            }
          }
        },
        {
          "name": "Get Expense Summary",
          "request": {
            "auth": {
              "type": "bearer",
              "bearer": [
                {
                  "key": "token",
                  "value": "{{authToken}}",
                  "type": "string"
                }
              ]
            },
            "method": "GET",
            "header": [],
            "url": {
              "raw": "{{baseUrl}}/expenses/summary",
              "host": ["{{baseUrl}}"],
              "path": ["expenses", "summary"]
            }
          }
        }
      ]
    },
    {
      "name": "Reports",
      "item": [
        {
          "name": "Dashboard Summary",
          "request": {
            "auth": {
              "type": "bearer",
              "bearer": [
                {
                  "key": "token",
                  "value": "{{authToken}}",
                  "type": "string"
                }
              ]
            },
            "method": "GET",
            "header": [],
            "url": {
              "raw": "{{baseUrl}}/reports/dashboard?start_date=2024-06-01&end_date=2024-06-30",
              "host": ["{{baseUrl}}"],
              "path": ["reports", "dashboard"],
              "query": [
                {
                  "key": "start_date",
                  "value": "2024-06-01"
                },
                {
                  "key": "end_date",
                  "value": "2024-06-30"
                }
              ]
            }
          }
        },
        {
          "name": "Sales Report",
          "request": {
            "auth": {
              "type": "bearer",
              "bearer": [
                {
                  "key": "token",
                  "value": "{{authToken}}",
                  "type": "string"
                }
              ]
            },
            "method": "GET",
            "header": [],
            "url": {
              "raw": "{{baseUrl}}/reports/sales?start_date=2024-06-01&end_date=2024-06-30&group_by=day",
              "host": ["{{baseUrl}}"],
              "path": ["reports", "sales"],
              "query": [
                {
                  "key": "start_date",
                  "value": "2024-06-01"
                },
                {
                  "key": "end_date",
                  "value": "2024-06-30"
                },
                {
                  "key": "group_by",
                  "value": "day",
                  "description": "Options: day, week, month"
                }
              ]
            }
          }
        },
        {
          "name": "Inventory Report",
          "request": {
            "auth": {
              "type": "bearer",
              "bearer": [
                {
                  "key": "token",
                  "value": "{{authToken}}",
                  "type": "string"
                }
              ]
            },
            "method": "GET",
            "header": [],
            "url": {
              "raw": "{{baseUrl}}/reports/inventory?low_stock_threshold=10",
              "host": ["{{baseUrl}}"],
              "path": ["reports", "inventory"],
              "query": [
                {
                  "key": "low_stock_threshold",
                  "value": "10"
                }
              ]
            }
          }
        },
        {
          "name": "Profit & Loss Report",
          "request": {
            "auth": {
              "type": "bearer",
              "bearer": [
                {
                  "key": "token",
                  "value": "{{authToken}}",
                  "type": "string"
                }
              ]
            },
            "method": "GET",
            "header": [],
            "url": {
              "raw": "{{baseUrl}}/reports/profit-loss?start_date=2024-06-01&end_date=2024-06-30",
              "host": ["{{baseUrl}}"],
              "path": ["reports", "profit-loss"],
              "query": [
                {
                  "key": "start_date",
                  "value": "2024-06-01"
                },
                {
                  "key": "end_date",
                  "value": "2024-06-30"
                }
              ]
            }
          }
        },
        {
          "name": "Product Performance Report",
          "request": {
            "auth": {
              "type": "bearer",
              "bearer": [
                {
                  "key": "token",
                  "value": "{{authToken}}",
                  "type": "string"
                }
              ]
            },
            "method": "GET",
            "header": [],
            "url": {
              "raw": "{{baseUrl}}/reports/product-performance?start_date=2024-06-01&end_date=2024-06-30",
              "host": ["{{baseUrl}}"],
              "path": ["reports", "product-performance"],
              "query": [
                {
                  "key": "start_date",
                  "value": "2024-06-01"
                },
                {
                  "key": "end_date",
                  "value": "2024-06-30"
                }
              ]
            }
          }
        }
      ]
    },
    {
      "name": "Purchases",
      "item": [
        {
          "name": "Add Purchase",
          "request": {
            "auth": {
              "type": "bearer",
              "bearer": [
                {
                  "key": "token",
                  "value": "{{authToken}}",
                  "type": "string"
                }
              ]
            },
            "method": "POST",
            "header": [
              {
                "key": "Content-Type",
                "value": "application/json"
              }
            ],
            "body": {
              "mode": "raw",
              "raw": "{\n    \"product_id\": 1,\n    \"quantity\": 100,\n    \"cost_price\": 800.00,\n    \"selling_price\": 1200.00\n}"
            },
            "url": {
              "raw": "{{baseUrl}}/purchases",
              "host": ["{{baseUrl}}"],
              "path": ["purchases"]
            }
          }
        },
        {
          "name": "Get All Purchases",
          "request": {
            "auth": {
              "type": "bearer",
              "bearer": [
                {
                  "key": "token",
                  "value": "{{authToken}}",
                  "type": "string"
                }
              ]
            },
            "method": "GET",
            "header": [],
            "url": {
              "raw": "{{baseUrl}}/purchases",
              "host": ["{{baseUrl}}"],
              "path": ["purchases"]
            }
          }
        },
        {
          "name": "Get Single Purchase",
          "request": {
            "auth": {
              "type": "bearer",
              "bearer": [
                {
                  "key": "token",
                  "value": "{{authToken}}",
                  "type": "string"
                }
              ]
            },
            "method": "GET",
            "header": [],
            "url": {
              "raw": "{{baseUrl}}/purchases/1",
              "host": ["{{baseUrl}}"],
              "path": ["purchases", "1"]
            }
          }
        },
        {
          "name": "Update Purchase",
          "request": {
            "auth": {
              "type": "bearer",
              "bearer": [
                {
                  "key": "token",
                  "value": "{{authToken}}",
                  "type": "string"
                }
              ]
            },
            "method": "PUT",
            "header": [
              {
                "key": "Content-Type",
                "value": "application/json"
              }
            ],
            "body": {
              "mode": "raw",
              "raw": "{\n    \"product_id\": 1,\n    \"quantity\": 120,\n    \"cost_price\": 780.00,\n    \"selling_price\": 1180.00\n}"
            },
            "url": {
              "raw": "{{baseUrl}}/purchases/1",
              "host": ["{{baseUrl}}"],
              "path": ["purchases", "1"]
            }
          }
        },
        {
          "name": "Delete Purchase",
          "request": {
            "auth": {
              "type": "bearer",
              "bearer": [
                {
                  "key": "token",
                  "value": "{{authToken}}",
                  "type": "string"
                }
              ]
            },
            "method": "DELETE",
            "header": [],
            "url": {
              "raw": "{{baseUrl}}/purchases/1",
              "host": ["{{baseUrl}}"],
              "path": ["purchases", "1"]
            }
          }
        },
        {
          "name": "Get Purchase Summary",
          "request": {
            "auth": {
              "type": "bearer",
              "bearer": [
                {
                  "key": "token",
                  "value": "{{authToken}}",
                  "type": "string"
                }
              ]
            },
            "method": "GET",
            "header": [],
            "url": {
              "raw": "{{baseUrl}}/purchases/summary?start_date=2024-01-01&end_date=2024-12-31",
              "host": ["{{baseUrl}}"],
              "path": ["purchases", "summary"],
              "query": [
                {
                  "key": "start_date",
                  "value": "2024-01-01"
                },
                {
                  "key": "end_date",
                  "value": "2024-12-31"
                }
              ]
            }
          }
        }
      ]
    }
  ]
}

